kadi/__init__.py
kadi/app.py
kadi/config.py
kadi/wsgi.py
kadi/assets/fonts/noto_emoji/LICENSE
kadi/assets/fonts/noto_emoji/NotoEmoji-Regular.ttf
kadi/assets/fonts/noto_sans/LICENSE
kadi/assets/fonts/noto_sans/NotoSans-Bold.ttf
kadi/assets/fonts/noto_sans/NotoSans-Italic.ttf
kadi/assets/fonts/noto_sans/NotoSans-Regular.ttf
kadi/assets/fonts/noto_sans_mono/LICENSE
kadi/assets/fonts/noto_sans_mono/NotoSansMono-Regular.ttf
kadi/assets/resources/opendefinition.json
kadi/assets/scripts/vendor.js
kadi/assets/scripts/app/main.js
kadi/assets/scripts/app/collections/view-collection.js
kadi/assets/scripts/app/records/add-files.js
kadi/assets/scripts/app/records/view-file.js
kadi/assets/scripts/app/records/view-record.js
kadi/assets/scripts/components/composables/dashboard-settings.js
kadi/assets/scripts/components/composables/resource-graph.js
kadi/assets/scripts/components/composables/undo-redo.js
kadi/assets/scripts/components/global/CardDeck.vue
kadi/assets/scripts/components/global/ClearButton.vue
kadi/assets/scripts/components/global/ClipboardButton.vue
kadi/assets/scripts/components/global/CollapseItem.vue
kadi/assets/scripts/components/global/ConfirmDialog.vue
kadi/assets/scripts/components/global/DynamicSelection.vue
kadi/assets/scripts/components/global/HungrySerpent.vue
kadi/assets/scripts/components/global/ImportForm.vue
kadi/assets/scripts/components/global/LanguagePrompt.vue
kadi/assets/scripts/components/global/ModalDialog.vue
kadi/assets/scripts/components/global/NavTabs.vue
kadi/assets/scripts/components/global/RangeSlider.vue
kadi/assets/scripts/components/global/ScopesViewer.vue
kadi/assets/scripts/components/global/ServiceManager.vue
kadi/assets/scripts/components/global/SubmissionForm.vue
kadi/assets/scripts/components/global/TermSearch.vue
kadi/assets/scripts/components/global/TooltipItem.vue
kadi/assets/scripts/components/global/datetime/DateTimePicker.vue
kadi/assets/scripts/components/global/datetime/FromNow.vue
kadi-1.8.0.dist-info/licenses/LICENSE
kadi-1.8.0.dist-info/METADATA
kadi-1.8.0.dist-info/WHEEL
kadi-1.8.0.dist-info/entry_points.txt
kadi-1.8.0.dist-info/top_level.txt
kadi-1.8.0.dist-info/RECORD
